micropymake/__init__.py
micropymake/main.py
micropymake/process.py
micropymake/test.py
MicroPyMake-0.0.4b3.dist-info/METADATA
MicroPyMake-0.0.4b3.dist-info/WHEEL
MicroPyMake-0.0.4b3.dist-info/entry_points.txt
MicroPyMake-0.0.4b3.dist-info/top_level.txt
MicroPyMake-0.0.4b3.dist-info/RECORD
